pylogfile/__init__.py
pylogfile/base.py
pylogfile/scripts/__init__.py
pylogfile/scripts/lumberjack.py
pylogfile-0.4.1.dist-info/licenses/LICENSE
pylogfile-0.4.1.dist-info/METADATA
pylogfile-0.4.1.dist-info/WHEEL
pylogfile-0.4.1.dist-info/entry_points.txt
pylogfile-0.4.1.dist-info/top_level.txt
pylogfile-0.4.1.dist-info/RECORD
