Metadata-Version: 2.4
Name: pylogfile
Version: 0.4.1
Summary: Universal log files for Python
Author-email: Grant Giesbrecht <grant.giesbrecht@colorado.edu>
License: BSD 3-Clause License
Project-URL: Homepage, https://github.com/Grant-Giesbrecht/pylogfile
Project-URL: Issues, https://github.com/Grant-Giesbrecht/pylogfile/issues
Classifier: Programming Language :: Python :: 3
Classifier: License :: OSI Approved :: MIT License
Classifier: Operating System :: OS Independent
Requires-Python: >=3.9
License-File: LICENSE
Requires-Dist: numpy>=2.0.0
Requires-Dist: h5py>=3.11.0
Requires-Dist: colorama>=0.4.6
Requires-Dist: importlib>=1.0.0
Dynamic: license-file
